MANIFEST.in
setup.py
src/taba/__init__.py
src/taba.egg-info/PKG-INFO
src/taba.egg-info/SOURCES.txt
src/taba.egg-info/dependency_links.txt
src/taba.egg-info/entry_points.txt
src/taba.egg-info/namespace_packages.txt
src/taba.egg-info/requires.txt
src/taba.egg-info/top_level.txt
src/taba/agent/__init__.py
src/taba/agent/agent.py
src/taba/agent/handlers.py
src/taba/agent/main.py
src/taba/client/__init__.py
src/taba/client/api.py
src/taba/client/async_engine.py
src/taba/client/engine.py
src/taba/client/gevent_engine.py
src/taba/client/thread_engine.py
src/taba/common/__init__.py
src/taba/common/transport.py
src/taba/common/transport_native.pyx
src/taba/common/validation.py
src/taba/handlers/__init__.py
src/taba/handlers/buffer.py
src/taba/handlers/counter_group.py
src/taba/handlers/dynamic_percentile_counter.py
src/taba/handlers/dynamic_percentile_counter_native.pyx
src/taba/handlers/expiry_gauge.py
src/taba/handlers/gauge.py
src/taba/handlers/moving_interval_percentile.py
src/taba/handlers/moving_interval_percentile_group.py
src/taba/handlers/noop_tab.py
src/taba/handlers/pyramid_counter.py
src/taba/handlers/pyramid_counter_native.pyx
src/taba/handlers/pyramid_group.py
src/taba/handlers/tab_handler.py
src/taba/handlers/tab_type.py
src/taba/handlers/totals_counter.py
src/taba/server/__init__.py
src/taba/server/backend.py
src/taba/server/frontend.py
src/taba/server/launch_taba_server.py
src/taba/server/request_handlers.py
src/taba/server/model/__init__.py
src/taba/server/model/client_storage.py
src/taba/server/model/identity_registry.py
src/taba/server/model/latency_tracker.py
src/taba/server/model/model_provider.py
src/taba/server/model/name_storage.py
src/taba/server/model/queue_registry.py
src/taba/server/model/state_manager.py
src/taba/server/model/tab_registry.py
src/taba/server/storage/__init__.py
src/taba/server/storage/double_index_storage.py
src/taba/server/storage/mapping_storage.py
src/taba/server/storage/memory_engine.py
src/taba/server/storage/redis_connection_pool.py
src/taba/server/storage/redis_engine.py
src/taba/server/storage/util.py
src/taba/third_party/__init__.py
src/taba/third_party/bottle.py
src/taba/util/__init__.py
src/taba/util/instrumentation_util.py
