Metadata-Version: 1.0
Name: taba
Version: 0.3.3
Summary: UNKNOWN
Home-page: http://github.com/tellapart/taba
Author: Kevin Ballard
Author-email: kevin@tellapart.com
License: Apache License, Version 2.0
Platform: UNKNOWN
Classifier: Development Status :: 4 - Beta
Classifier: Natural Language :: English
Classifier: Operating System :: POSIX
